pymeshlab-2025.7.post1.data/purelib/pymeshlab/__init__.py
pymeshlab-2025.7.post1.data/purelib/pymeshlab/keys.txt
pymeshlab-2025.7.post1.data/purelib/pymeshlab/pmeshlab.cpython-312-darwin.so
pymeshlab-2025.7.post1.data/purelib/pymeshlab/polyscope_functions.py
pymeshlab-2025.7.post1.data/purelib/pymeshlab/replacer.py
pymeshlab-2025.7.post1.data/purelib/pymeshlab/setup.cfg
pymeshlab-2025.7.post1.data/purelib/pymeshlab/Frameworks/lib3mf.2.4.1.0.dylib
pymeshlab-2025.7.post1.data/purelib/pymeshlab/Frameworks/lib3mf.2.dylib
pymeshlab-2025.7.post1.data/purelib/pymeshlab/Frameworks/lib3mf.dylib
pymeshlab-2025.7.post1.data/purelib/pymeshlab/Frameworks/libIDTF.a
pymeshlab-2025.7.post1.data/purelib/pymeshlab/Frameworks/libIFXCore.so
pymeshlab-2025.7.post1.data/purelib/pymeshlab/Frameworks/libIFXExporting.so
pymeshlab-2025.7.post1.data/purelib/pymeshlab/Frameworks/libIFXScheduling.so
pymeshlab-2025.7.post1.data/purelib/pymeshlab/Frameworks/libboost_atomic.dylib
pymeshlab-2025.7.post1.data/purelib/pymeshlab/Frameworks/libboost_chrono.dylib
pymeshlab-2025.7.post1.data/purelib/pymeshlab/Frameworks/libboost_container.dylib
pymeshlab-2025.7.post1.data/purelib/pymeshlab/Frameworks/libboost_date_time.dylib
pymeshlab-2025.7.post1.data/purelib/pymeshlab/Frameworks/libboost_thread.dylib
pymeshlab-2025.7.post1.data/purelib/pymeshlab/Frameworks/libembree4.4.dylib
pymeshlab-2025.7.post1.data/purelib/pymeshlab/Frameworks/libexternal-glew.dylib
pymeshlab-2025.7.post1.data/purelib/pymeshlab/Frameworks/libfreetype.6.dylib
pymeshlab-2025.7.post1.data/purelib/pymeshlab/Frameworks/libglib-2.0.0.dylib
pymeshlab-2025.7.post1.data/purelib/pymeshlab/Frameworks/libgmp.10.dylib
pymeshlab-2025.7.post1.data/purelib/pymeshlab/Frameworks/libgmpxx.4.dylib
pymeshlab-2025.7.post1.data/purelib/pymeshlab/Frameworks/libgthread-2.0.0.dylib
pymeshlab-2025.7.post1.data/purelib/pymeshlab/Frameworks/libintl.8.dylib
pymeshlab-2025.7.post1.data/purelib/pymeshlab/Frameworks/libjpeg.8.dylib
pymeshlab-2025.7.post1.dist-info/licenses/LICENSE
pymeshlab-2025.7.post1.dist-info/METADATA
pymeshlab-2025.7.post1.dist-info/WHEEL
pymeshlab-2025.7.post1.dist-info/top_level.txt
pymeshlab-2025.7.post1.dist-info/RECORD
