Metadata-Version: 2.4
Name: pymeshlab
Version: 2025.7.post1
Summary: A Python interface to MeshLab
Home-page: https://github.com/cnr-isti-vclab/PyMeshLab
Author: Alessandro Muntoni, Paolo Cignoni
Author-email: alessandro.muntoni@isti.cnr.it
License: GPL3
License-File: LICENSE
Requires-Dist: numpy
Requires-Dist: msvc-runtime
Dynamic: author
Dynamic: author-email
Dynamic: description
Dynamic: description-content-type
Dynamic: home-page
Dynamic: license
Dynamic: license-file
Dynamic: requires-dist
Dynamic: summary
